{
      "conditions": [
          {
              "condition_name": "allow_auto_merge",
              "condition_value": false
          }
      ],
      "metadata": {
          "branch": "main",
          "repository": "policies_test",
          "owner": "Samra10",
          "repository_url": "https://github.com/Samra10/policies_test.git",
          "ssd_secret": {
              "github": {
                  "rest_api_url": "https://api.github.com",
                  "token": "xxxxx",
                  "workflowName": "Insecure Approved Action Workflow"
              }
          }
      }
  }
  